<?xml version='1.0' encoding='utf-8'?>
<routes>
  <route control_mode="replay" id="2023-04-04-16-12-17_44_0" model="walker.pedestrian.0007" role="walker" snap_to_road="false" town="ucla_v2">
    <waypoint pitch="0.000000" roll="0.000000" time="0.000000" x="-485.796773" y="17.879819" yaw="-43.729120" z="9.587345" />
    <waypoint pitch="0.000000" roll="0.000000" time="0.100000" x="-485.792823" y="17.845919" yaw="-43.723347" z="9.587819" />
    <waypoint pitch="0.000000" roll="0.000000" time="0.200000" x="-485.787574" y="17.804138" yaw="-43.729104" z="9.588219" />
    <waypoint pitch="0.000000" roll="0.000000" time="0.300000" x="-485.780189" y="17.750301" yaw="-43.723396" z="9.589381" />
    <waypoint pitch="0.000000" roll="0.000000" time="0.400000" x="-485.776117" y="17.722609" yaw="-43.728933" z="9.590807" />
    <waypoint pitch="0.000000" roll="0.000000" time="0.500000" x="-485.755254" y="17.596778" yaw="-43.723396" z="9.593679" />
    <waypoint pitch="0.000000" roll="0.000000" time="0.600000" x="-485.736414" y="17.499339" yaw="-43.729126" z="9.596511" />
    <waypoint pitch="0.000000" roll="0.000000" time="0.700000" x="-485.690222" y="17.103137" yaw="-43.723387" z="9.599227" />
    <waypoint pitch="0.000000" roll="0.000000" time="0.800000" x="-485.687315" y="17.059334" yaw="-43.723341" z="9.601622" />
    <waypoint pitch="0.000000" roll="0.000000" time="0.900000" x="-485.685453" y="17.034344" yaw="-43.723368" z="9.603867" />
    <waypoint pitch="0.000000" roll="0.000000" time="1.000000" x="-485.683635" y="17.011675" yaw="-43.729095" z="9.604781" />
    <waypoint pitch="0.000000" roll="0.000000" time="1.100000" x="-485.677986" y="16.949128" yaw="-43.723336" z="9.605816" />
    <waypoint pitch="0.000000" roll="0.000000" time="1.200000" x="-485.670518" y="16.878786" yaw="-43.729121" z="9.606852" />
    <waypoint pitch="0.000000" roll="0.000000" time="1.300000" x="-485.661481" y="16.805556" yaw="-43.723350" z="9.608131" />
    <waypoint pitch="0.000000" roll="0.000000" time="1.400000" x="-485.658793" y="16.785588" yaw="-43.729098" z="9.609156" />
    <waypoint pitch="0.000000" roll="0.000000" time="1.500000" x="-485.645928" y="16.698443" yaw="-43.717705" z="9.610391" />
    <waypoint pitch="0.000000" roll="0.000000" time="1.600000" x="-485.642492" y="16.677081" yaw="-43.729117" z="9.611430" />
    <waypoint pitch="0.000000" roll="0.000000" time="1.700000" x="-485.625106" y="16.578080" yaw="-43.723419" z="9.612785" />
    <waypoint pitch="0.000000" roll="0.000000" time="1.800000" x="-485.616615" y="16.553277" yaw="-43.729114" z="9.614807" />
    <waypoint pitch="0.000000" roll="0.000000" time="1.900000" x="-485.556053" y="16.482264" yaw="-43.723393" z="9.617090" />
    <waypoint pitch="0.000000" roll="0.000000" time="2.000000" x="-485.482592" y="16.217466" yaw="-43.729158" z="9.619144" />
    <waypoint pitch="0.000000" roll="0.000000" time="2.100000" x="-485.431892" y="16.159076" yaw="-43.723383" z="9.621458" />
    <waypoint pitch="0.000000" roll="0.000000" time="2.200000" x="-485.376444" y="16.099432" yaw="-43.729129" z="9.623713" />
    <waypoint pitch="0.000000" roll="0.000000" time="2.300000" x="-485.337917" y="16.014189" yaw="-43.717677" z="9.625111" />
    <waypoint pitch="0.000000" roll="0.000000" time="2.400000" x="-485.295066" y="15.955596" yaw="-43.729103" z="9.626559" />
    <waypoint pitch="0.000000" roll="0.000000" time="2.500000" x="-485.261062" y="15.898372" yaw="-43.717660" z="9.628037" />
    <waypoint pitch="0.000000" roll="0.000000" time="2.600000" x="-485.226114" y="15.825771" yaw="-43.729106" z="9.629371" />
    <waypoint pitch="0.000000" roll="0.000000" time="2.700000" x="-485.175726" y="15.758311" yaw="-43.717678" z="9.630851" />
    <waypoint pitch="0.000000" roll="0.000000" time="2.800000" x="-485.157751" y="15.705830" yaw="-43.729244" z="9.632575" />
    <waypoint pitch="0.000000" roll="0.000000" time="2.900000" x="-485.115880" y="15.610713" yaw="-43.717742" z="9.634956" />
    <waypoint pitch="0.000000" roll="0.000000" time="3.000000" x="-485.060274" y="15.495393" yaw="-43.729274" z="9.637505" />
    <waypoint pitch="0.000000" roll="0.000000" time="3.100000" x="-485.000587" y="15.263290" yaw="-43.717735" z="9.640194" />
    <waypoint pitch="0.000000" roll="0.000000" time="3.200000" x="-484.943280" y="15.154813" yaw="-43.729210" z="9.642849" />
    <waypoint pitch="0.000000" roll="0.000000" time="3.300000" x="-484.911193" y="15.069260" yaw="-43.717743" z="9.645490" />
    <waypoint pitch="0.000000" roll="0.000000" time="3.400000" x="-484.890180" y="14.980266" yaw="-43.729177" z="9.647468" />
    <waypoint pitch="0.000000" roll="0.000000" time="3.500000" x="-484.877532" y="14.863036" yaw="-43.717752" z="9.649494" />
    <waypoint pitch="0.000000" roll="0.000000" time="3.600000" x="-484.855082" y="14.790699" yaw="-43.729097" z="9.651553" />
    <waypoint pitch="0.000000" roll="0.000000" time="3.700000" x="-484.821862" y="14.666998" yaw="-43.717632" z="9.654184" />
    <waypoint pitch="0.000000" roll="0.000000" time="3.800000" x="-484.787335" y="14.574077" yaw="-43.723316" z="9.656694" />
    <waypoint pitch="0.000000" roll="0.000000" time="3.900000" x="-484.739972" y="14.346158" yaw="-43.717587" z="9.659420" />
    <waypoint pitch="0.000000" roll="0.000000" time="4.000000" x="-484.699893" y="14.262425" yaw="-43.729082" z="9.662115" />
    <waypoint pitch="0.000000" roll="0.000000" time="4.100000" x="-484.659793" y="14.138532" yaw="-43.717547" z="9.665203" />
    <waypoint pitch="0.000000" roll="0.000000" time="4.200000" x="-484.622209" y="14.023185" yaw="-43.723305" z="9.667953" />
    <waypoint pitch="0.000000" roll="0.000000" time="4.300000" x="-484.611891" y="13.829472" yaw="-43.717577" z="9.670904" />
    <waypoint pitch="0.000000" roll="0.000000" time="4.400000" x="-484.589308" y="13.682367" yaw="-43.723335" z="9.674003" />
    <waypoint pitch="0.000000" roll="0.000000" time="4.500000" x="-484.562968" y="13.547003" yaw="-43.723344" z="9.677063" />
    <waypoint pitch="0.000000" roll="0.000000" time="4.600000" x="-484.542116" y="13.384220" yaw="-43.723357" z="9.679741" />
    <waypoint pitch="0.000000" roll="0.000000" time="4.700000" x="-484.510019" y="13.277800" yaw="-43.717633" z="9.682255" />
    <waypoint pitch="0.000000" roll="0.000000" time="4.800000" x="-484.482745" y="13.180985" yaw="-43.723373" z="9.684212" />
    <waypoint pitch="0.000000" roll="0.000000" time="4.900000" x="-484.461825" y="13.074281" yaw="-43.723388" z="9.686301" />
    <waypoint pitch="0.000000" roll="0.000000" time="5.000000" x="-484.429006" y="13.032962" yaw="-43.729054" z="9.688427" />
    <waypoint pitch="0.000000" roll="0.000000" time="5.100000" x="-484.383405" y="12.885921" yaw="-43.723347" z="9.690711" />
    <waypoint pitch="0.000000" roll="0.000000" time="5.200000" x="-484.353958" y="12.769364" yaw="-43.729078" z="9.692941" />
    <waypoint pitch="0.000000" roll="0.000000" time="5.300000" x="-484.327148" y="12.633821" yaw="-43.717622" z="9.696052" />
    <waypoint pitch="0.000000" roll="0.000000" time="5.400000" x="-484.325215" y="12.538168" yaw="-43.723328" z="9.698795" />
    <waypoint pitch="0.000000" roll="0.000000" time="5.500000" x="-484.281497" y="12.327544" yaw="-43.723296" z="9.701575" />
    <waypoint pitch="0.000000" roll="0.000000" time="5.600000" x="-484.247329" y="12.225963" yaw="-43.723335" z="9.704495" />
    <waypoint pitch="0.000000" roll="0.000000" time="5.700000" x="-484.245747" y="12.097522" yaw="-43.723327" z="9.707674" />
    <waypoint pitch="0.000000" roll="0.000000" time="5.800000" x="-484.170015" y="11.935580" yaw="-43.723305" z="9.710365" />
    <waypoint pitch="0.000000" roll="0.000000" time="5.900000" x="-484.161381" y="11.777821" yaw="-43.717554" z="9.713251" />
    <waypoint pitch="0.000000" roll="0.000000" time="6.000000" x="-484.134571" y="11.684758" yaw="-43.723328" z="9.716261" />
    <waypoint pitch="0.000000" roll="0.000000" time="6.100000" x="-484.131506" y="11.531582" yaw="-43.717526" z="9.719164" />
    <waypoint pitch="0.000000" roll="0.000000" time="6.200000" x="-484.099497" y="11.376760" yaw="-43.723266" z="9.721891" />
    <waypoint pitch="0.000000" roll="0.000000" time="6.300000" x="-484.086597" y="11.233254" yaw="-43.717506" z="9.724751" />
    <waypoint pitch="0.000000" roll="0.000000" time="6.400000" x="-484.071967" y="11.118952" yaw="-43.472917" z="9.727499" />
    <waypoint pitch="0.000000" roll="0.000000" time="6.500000" x="-484.038949" y="10.994059" yaw="-43.341883" z="9.730173" />
    <waypoint pitch="0.000000" roll="0.000000" time="6.600000" x="-484.029096" y="10.869108" yaw="-43.222475" z="9.732671" />
    <waypoint pitch="0.000000" roll="0.000000" time="6.700000" x="-484.000704" y="10.731786" yaw="-43.091555" z="9.735751" />
    <waypoint pitch="0.000000" roll="0.000000" time="6.800000" x="-483.980539" y="10.632960" yaw="-42.972176" z="9.738263" />
    <waypoint pitch="0.000000" roll="0.000000" time="6.900000" x="-483.981589" y="10.373353" yaw="-42.841291" z="9.741084" />
    <waypoint pitch="0.000000" roll="0.000000" time="7.000000" x="-483.933502" y="10.389971" yaw="-42.721882" z="9.743934" />
    <waypoint pitch="0.000000" roll="0.000000" time="7.100000" x="-483.922690" y="10.189912" yaw="-42.590975" z="9.746992" />
    <waypoint pitch="0.000000" roll="0.000000" time="7.200000" x="-483.940046" y="10.039038" yaw="-42.471542" z="9.749531" />
    <waypoint pitch="0.000000" roll="0.000000" time="7.300000" x="-483.943017" y="9.886331" yaw="-42.340617" z="9.752671" />
    <waypoint pitch="0.000000" roll="0.000000" time="7.400000" x="-483.965905" y="9.751529" yaw="-40.969359" z="9.755715" />
    <waypoint pitch="0.000000" roll="0.000000" time="7.500000" x="-483.939826" y="9.617600" yaw="-40.462881" z="9.758757" />
    <waypoint pitch="0.000000" roll="0.000000" time="7.600000" x="-483.915764" y="9.442617" yaw="-39.842737" z="9.761578" />
    <waypoint pitch="0.000000" roll="0.000000" time="7.700000" x="-483.923296" y="9.294180" yaw="-39.211193" z="9.764286" />
    <waypoint pitch="0.000000" roll="0.000000" time="7.800000" x="-483.930241" y="9.195015" yaw="-38.591063" z="9.766766" />
    <waypoint pitch="0.000000" roll="0.000000" time="7.900000" x="-483.925749" y="9.091771" yaw="-38.209885" z="9.769055" />
    <waypoint pitch="0.000000" roll="0.000000" time="8.000000" x="-483.916839" y="9.011456" yaw="-37.715063" z="9.771355" />
    <waypoint pitch="0.000000" roll="0.000000" time="8.100000" x="-483.896929" y="8.882636" yaw="-37.208779" z="9.773722" />
    <waypoint pitch="0.000000" roll="0.000000" time="8.200000" x="-483.898802" y="8.732179" yaw="-36.713958" z="9.776570" />
    <waypoint pitch="0.000000" roll="0.000000" time="8.300000" x="-483.864560" y="8.621451" yaw="-36.207772" z="9.779699" />
    <waypoint pitch="0.000000" roll="0.000000" time="8.400000" x="-483.867900" y="8.399069" yaw="-35.713039" z="9.774556" />
    <waypoint pitch="0.000000" roll="0.000000" time="8.500000" x="-483.847719" y="8.251409" yaw="-35.201170" z="9.777616" />
    <waypoint pitch="0.000000" roll="0.000000" time="8.600000" x="-484.052398" y="10.126884" yaw="-59.753823" z="9.772448" />
    <waypoint pitch="0.000000" roll="0.000000" time="8.700000" x="-483.851495" y="7.986094" yaw="-34.206154" z="9.766878" />
    <waypoint pitch="0.000000" roll="0.000000" time="8.800000" x="-484.080736" y="9.863890" yaw="-59.679453" z="9.761268" />
    <waypoint pitch="0.000000" roll="0.000000" time="8.900000" x="-484.110094" y="9.736999" yaw="-59.697880" z="9.771594" />
    <waypoint pitch="0.000000" roll="0.000000" time="9.000000" x="-484.061849" y="9.602414" yaw="-59.737621" z="9.766395" />
    <waypoint pitch="0.000000" roll="0.000000" time="9.100000" x="-483.835123" y="7.617134" yaw="-32.204974" z="9.777156" />
    <waypoint pitch="0.000000" roll="0.000000" time="9.200000" x="-483.995810" y="9.245110" yaw="-59.826363" z="9.780311" />
    <waypoint pitch="0.000000" roll="0.000000" time="9.300000" x="-483.808507" y="7.254180" yaw="-31.204624" z="9.791048" />
    <waypoint pitch="0.000000" roll="0.000000" time="9.400000" x="-483.973911" y="8.979266" yaw="-59.972969" z="9.794007" />
    <waypoint pitch="0.000000" roll="0.000000" time="9.500000" x="-483.798753" y="6.997515" yaw="-30.204288" z="9.804186" />
    <waypoint pitch="0.000000" roll="0.000000" time="9.600000" x="-483.781721" y="6.896793" yaw="-29.709935" z="9.806681" />
    <waypoint pitch="0.000000" roll="0.000000" time="9.700000" x="-483.777490" y="6.771644" yaw="-29.204099" z="9.817316" />
    <waypoint pitch="0.000000" roll="0.000000" time="9.800000" x="-483.775217" y="6.645588" yaw="-28.709866" z="9.820219" />
    <waypoint pitch="0.000000" roll="0.000000" time="9.900000" x="-483.750706" y="6.394520" yaw="-28.204056" z="9.823163" />
    <waypoint pitch="0.000000" roll="0.000000" time="10.000000" x="-483.708571" y="6.295916" yaw="-88.483699" z="9.826098" />
    <waypoint pitch="0.000000" roll="0.000000" time="10.100000" x="-483.706914" y="6.182882" yaw="-88.477974" z="9.821778" />
    <waypoint pitch="0.000000" roll="0.000000" time="10.200000" x="-483.720844" y="6.057624" yaw="-88.489436" z="9.824175" />
    <waypoint pitch="0.000000" roll="0.000000" time="10.300000" x="-483.832059" y="7.699541" yaw="-88.598917" z="9.826676" />
    <waypoint pitch="0.000000" roll="0.000000" time="10.400000" x="-483.718610" y="5.809672" yaw="-88.489434" z="9.829174" />
    <waypoint pitch="0.000000" roll="0.000000" time="10.500000" x="-483.704059" y="5.681998" yaw="-88.477974" z="9.832182" />
    <waypoint pitch="0.000000" roll="0.000000" time="10.600000" x="-483.701593" y="5.569948" yaw="-88.483705" z="9.842378" />
    <waypoint pitch="0.000000" roll="0.000000" time="10.700000" x="-483.681467" y="5.323319" yaw="-88.477976" z="9.845390" />
    <waypoint pitch="0.000000" roll="0.000000" time="10.800000" x="-483.683168" y="5.213144" yaw="-88.483704" z="9.855491" />
    <waypoint pitch="0.000000" roll="0.000000" time="10.900000" x="-483.685395" y="5.073838" yaw="-88.477972" z="9.858529" />
    <waypoint pitch="0.000000" roll="0.000000" time="11.000000" x="-483.611869" y="3.211730" yaw="-85.965638" z="9.861015" />
    <waypoint pitch="0.000000" roll="0.000000" time="11.100000" x="-483.676001" y="4.826368" yaw="-88.477974" z="9.863578" />
    <waypoint pitch="0.000000" roll="0.000000" time="11.200000" x="-483.667915" y="4.714001" yaw="-88.483704" z="9.872791" />
    <waypoint pitch="0.000000" roll="0.000000" time="11.300000" x="-483.645214" y="4.588138" yaw="-88.472247" z="9.868646" />
    <waypoint pitch="0.000000" roll="0.000000" time="11.400000" x="-483.567464" y="2.824797" yaw="-86.061145" z="9.871545" />
    <waypoint pitch="0.000000" roll="0.000000" time="11.500000" x="-483.590806" y="4.232795" yaw="-88.477972" z="9.881073" />
    <waypoint pitch="0.000000" roll="0.000000" time="11.600000" x="-483.585110" y="4.125600" yaw="-88.483704" z="9.890426" />
    <waypoint pitch="0.000000" roll="0.000000" time="11.700000" x="-483.509564" y="2.392766" yaw="-85.969692" z="9.886430" />
    <waypoint pitch="0.000000" roll="0.000000" time="11.800000" x="-483.489598" y="2.309900" yaw="-86.031318" z="9.888526" />
    <waypoint pitch="0.000000" roll="0.000000" time="11.900000" x="-483.558795" y="3.807564" yaw="-88.477961" z="9.890587" />
    <waypoint pitch="0.000000" roll="0.000000" time="12.000000" x="-483.547027" y="3.723188" yaw="-88.483705" z="9.886371" />
    <waypoint pitch="0.000000" roll="0.000000" time="12.100000" x="-483.529073" y="3.626668" yaw="-88.477970" z="9.882384" />
    <waypoint pitch="0.000000" roll="0.000000" time="12.200000" x="-483.501769" y="3.429611" yaw="-88.483707" z="9.883589" />
    <waypoint pitch="0.000000" roll="0.000000" time="12.300000" x="-483.492861" y="3.289112" yaw="-88.477971" z="9.885011" />
  </route>
</routes>