<?xml version='1.0' encoding='utf-8'?>
<routes>
  <route control_mode="replay" id="2023-04-05-16-18-26_15_0" model="walker.pedestrian.0002" role="walker" snap_to_road="false" town="ucla_v2">
    <waypoint pitch="0.000000" roll="0.000000" time="0.000000" x="-491.639135" y="-25.724534" yaw="-179.596719" z="10.294851" />
    <waypoint pitch="0.000000" roll="0.000000" time="0.100000" x="-491.819684" y="-25.702657" yaw="-179.631138" z="10.294047" />
    <waypoint pitch="0.000000" roll="0.000000" time="0.200000" x="-491.958271" y="-25.638209" yaw="-179.619677" z="10.293993" />
    <waypoint pitch="0.000000" roll="0.000000" time="0.300000" x="-492.101078" y="-25.638281" yaw="-179.619677" z="10.292603" />
    <waypoint pitch="0.000000" roll="0.000000" time="0.400000" x="-491.911042" y="-25.628827" yaw="-179.608205" z="10.291374" />
    <waypoint pitch="0.000000" roll="0.000000" time="0.500000" x="-492.285409" y="-25.616616" yaw="-179.585219" z="10.290183" />
    <waypoint pitch="0.000000" roll="0.000000" time="0.600000" x="-492.366204" y="-25.603200" yaw="-179.619677" z="10.289181" />
    <waypoint pitch="0.000000" roll="0.000000" time="0.700000" x="-492.487301" y="-25.694413" yaw="-179.619677" z="10.287372" />
    <waypoint pitch="0.000000" roll="0.000000" time="0.800000" x="-492.546861" y="-25.717577" yaw="-179.642589" z="10.286156" />
    <waypoint pitch="0.000000" roll="0.000000" time="0.900000" x="-492.715644" y="-25.753509" yaw="-179.619677" z="10.284918" />
    <waypoint pitch="0.000000" roll="0.000000" time="1.000000" x="-492.825975" y="-25.744867" yaw="-179.619677" z="10.283811" />
    <waypoint pitch="0.000000" roll="0.000000" time="1.100000" x="-492.917233" y="-25.684908" yaw="-179.619677" z="10.282595" />
    <waypoint pitch="0.000000" roll="0.000000" time="1.200000" x="-492.979420" y="-25.743527" yaw="-179.619677" z="10.281772" />
    <waypoint pitch="0.000000" roll="0.000000" time="1.300000" x="-493.087545" y="-25.705279" yaw="-179.608205" z="10.280399" />
    <waypoint pitch="0.000000" roll="0.000000" time="1.400000" x="-493.080910" y="-25.674801" yaw="-179.619677" z="10.279112" />
    <waypoint pitch="0.000000" roll="0.000000" time="1.500000" x="-493.436470" y="-25.675545" yaw="-179.619677" z="10.278109" />
    <waypoint pitch="0.000000" roll="0.000000" time="1.600000" x="-493.488864" y="-25.658331" yaw="-179.619677" z="10.276998" />
    <waypoint pitch="0.000000" roll="0.000000" time="1.700000" x="-493.424666" y="-25.704365" yaw="-179.596719" z="10.275579" />
    <waypoint pitch="0.000000" roll="0.000000" time="1.800000" x="-493.581214" y="-25.658772" yaw="-179.619677" z="10.274716" />
    <waypoint pitch="0.000000" roll="0.000000" time="1.900000" x="-493.711676" y="-25.692807" yaw="-179.619677" z="10.273938" />
    <waypoint pitch="0.000000" roll="0.000000" time="2.000000" x="-493.823746" y="-25.702348" yaw="-177.105731" z="10.272869" />
    <waypoint pitch="0.000000" roll="0.000000" time="2.100000" x="-493.837429" y="-25.705524" yaw="-175.939962" z="10.271994" />
    <waypoint pitch="0.000000" roll="0.000000" time="2.200000" x="-493.900306" y="-25.711883" yaw="-174.695338" z="10.271257" />
    <waypoint pitch="0.000000" roll="0.000000" time="2.300000" x="-493.962301" y="-25.715788" yaw="-173.483643" z="10.270127" />
    <waypoint pitch="0.000000" roll="0.000000" time="2.400000" x="-494.024737" y="-25.720919" yaw="-174.708201" z="10.268621" />
    <waypoint pitch="0.000000" roll="0.000000" time="2.500000" x="-494.265654" y="-25.745954" yaw="-174.752327" z="10.266854" />
    <waypoint pitch="0.000000" roll="0.000000" time="2.600000" x="-494.422826" y="-25.706736" yaw="-174.925445" z="10.265098" />
    <waypoint pitch="0.000000" roll="0.000000" time="2.700000" x="-494.579999" y="-25.667519" yaw="-174.821881" z="10.263195" />
    <waypoint pitch="0.000000" roll="0.000000" time="2.800000" x="-494.636201" y="-25.632920" yaw="-174.861333" z="10.261914" />
    <waypoint pitch="0.000000" roll="0.000000" time="2.900000" x="-494.751704" y="-25.710047" yaw="-175.017294" z="10.260422" />
    <waypoint pitch="0.000000" roll="0.000000" time="3.000000" x="-494.757445" y="-25.574459" yaw="-178.079508" z="10.259509" />
    <waypoint pitch="0.000000" roll="0.000000" time="3.100000" x="-494.996165" y="-25.561627" yaw="-177.619818" z="10.258299" />
    <waypoint pitch="0.000000" roll="0.000000" time="3.200000" x="-494.930093" y="-25.605910" yaw="-178.148990" z="10.257443" />
    <waypoint pitch="0.000000" roll="0.000000" time="3.300000" x="-495.101118" y="-25.575836" yaw="-178.237038" z="10.256036" />
    <waypoint pitch="0.000000" roll="0.000000" time="3.400000" x="-495.080922" y="-25.554414" yaw="-177.767230" z="10.254999" />
    <waypoint pitch="0.000000" roll="0.000000" time="3.500000" x="-495.298277" y="-25.677243" yaw="-176.821224" z="10.253479" />
    <waypoint pitch="0.000000" roll="0.000000" time="3.600000" x="-495.394064" y="-25.703492" yaw="-176.659599" z="10.251639" />
    <waypoint pitch="0.000000" roll="0.000000" time="3.700000" x="-495.513421" y="-25.688330" yaw="-175.624399" z="10.249626" />
    <waypoint pitch="0.000000" roll="0.000000" time="3.800000" x="-495.807413" y="-25.707363" yaw="-176.109248" z="10.248080" />
    <waypoint pitch="0.000000" roll="0.000000" time="3.900000" x="-495.852711" y="-25.623018" yaw="-178.580606" z="10.246518" />
    <waypoint pitch="0.000000" roll="0.000000" time="4.000000" x="-495.891951" y="-25.624703" yaw="-179.764127" z="10.245165" />
    <waypoint pitch="0.000000" roll="0.000000" time="4.100000" x="-495.994057" y="-25.635680" yaw="179.051875" z="10.243662" />
    <waypoint pitch="0.000000" roll="0.000000" time="4.200000" x="-496.030358" y="-25.647466" yaw="179.872574" z="10.242278" />
    <waypoint pitch="0.000000" roll="0.000000" time="4.300000" x="-496.358784" y="-25.754634" yaw="-179.306824" z="10.241478" />
    <waypoint pitch="0.000000" roll="0.000000" time="10.200000" x="-496.358784" y="-25.754634" yaw="-179.306824" z="10.240587" />
  </route>
</routes>