<?xml version='1.0' encoding='utf-8'?>
<routes>
  <route control_mode="replay" id="2023-04-04-15-47-17_19_1" model="walker.pedestrian.0006" role="walker" snap_to_road="false" town="ucla_v2">
    <waypoint pitch="0.000000" roll="0.000000" time="0.000000" x="-496.151605" y="-25.351560" yaw="0.190392" z="10.243592" />
    <waypoint pitch="0.000000" roll="0.000000" time="8.000000" x="-496.151605" y="-25.351560" yaw="0.190392" z="10.244795" />
    <waypoint pitch="0.000000" roll="0.000000" time="8.300000" x="-495.789356" y="-25.353392" yaw="0.116314" z="10.245831" />
    <waypoint pitch="0.000000" roll="0.000000" time="8.400000" x="-495.668607" y="-25.354003" yaw="0.091622" z="10.247693" />
    <waypoint pitch="0.000000" roll="0.000000" time="8.500000" x="-495.547793" y="-25.366025" yaw="0.066950" z="10.249816" />
    <waypoint pitch="0.000000" roll="0.000000" time="8.600000" x="-495.447193" y="-25.392042" yaw="0.042278" z="10.251649" />
    <waypoint pitch="0.000000" roll="0.000000" time="8.700000" x="-495.346592" y="-25.418060" yaw="0.017606" z="10.253433" />
    <waypoint pitch="0.000000" roll="0.000000" time="8.800000" x="-495.085146" y="-25.388072" yaw="-0.076326" z="10.255166" />
    <waypoint pitch="0.000000" roll="0.000000" time="8.900000" x="-494.983611" y="-25.348072" yaw="-0.040396" z="10.256897" />
    <waypoint pitch="0.000000" roll="0.000000" time="9.000000" x="-494.882077" y="-25.308072" yaw="-0.073726" z="10.258629" />
    <waypoint pitch="0.000000" roll="0.000000" time="9.100000" x="-494.782085" y="-25.308201" yaw="-0.073726" z="10.259939" />
    <waypoint pitch="0.000000" roll="0.000000" time="9.200000" x="-494.682093" y="-25.308330" yaw="-0.073726" z="10.261245" />
    <waypoint pitch="0.000000" roll="0.000000" time="9.300000" x="-494.582101" y="-25.308458" yaw="-0.073726" z="10.262598" />
    <waypoint pitch="0.000000" roll="0.000000" time="9.400000" x="-494.482109" y="-25.308587" yaw="-0.157965" z="10.264003" />
    <waypoint pitch="0.000000" roll="0.000000" time="9.500000" x="-494.362289" y="-25.308907" yaw="-0.053340" z="10.265459" />
    <waypoint pitch="0.000000" roll="0.000000" time="9.600000" x="-494.242469" y="-25.309227" yaw="-0.032955" z="10.266966" />
    <waypoint pitch="0.000000" roll="0.000000" time="9.700000" x="-494.122649" y="-25.309548" yaw="-0.012570" z="10.268516" />
    <waypoint pitch="0.000000" roll="0.000000" time="9.800000" x="-494.002829" y="-25.309868" yaw="0.007815" z="10.270022" />
    <waypoint pitch="0.000000" roll="0.000000" time="9.900000" x="-493.883009" y="-25.310188" yaw="0.028201" z="10.271585" />
    <waypoint pitch="0.000000" roll="0.000000" time="10.000000" x="-493.763189" y="-25.310508" yaw="-0.036362" z="10.273014" />
    <waypoint pitch="0.000000" roll="0.000000" time="10.100000" x="-493.599382" y="-25.330276" yaw="0.068653" z="10.274397" />
    <waypoint pitch="0.000000" roll="0.000000" time="10.200000" x="-493.520519" y="-25.526297" yaw="0.142805" z="10.275747" />
    <waypoint pitch="0.000000" roll="0.000000" time="10.300000" x="-493.402645" y="-25.618874" yaw="0.108786" z="10.277096" />
    <waypoint pitch="0.000000" roll="0.000000" time="10.400000" x="-493.282678" y="-25.594669" yaw="0.277628" z="10.278343" />
    <waypoint pitch="0.000000" roll="0.000000" time="10.500000" x="-493.164541" y="-25.436546" yaw="0.338298" z="10.279678" />
    <waypoint pitch="0.000000" roll="0.000000" time="10.600000" x="-493.045783" y="-25.471439" yaw="0.398969" z="10.281014" />
    <waypoint pitch="0.000000" roll="0.000000" time="10.700000" x="-492.926894" y="-25.466396" yaw="0.459639" z="10.282348" />
    <waypoint pitch="0.000000" roll="0.000000" time="10.800000" x="-492.808006" y="-25.481321" yaw="0.520309" z="10.283684" />
    <waypoint pitch="0.000000" roll="0.000000" time="10.900000" x="-492.689901" y="-25.422109" yaw="0.586365" z="10.285019" />
    <waypoint pitch="0.000000" roll="0.000000" time="11.000000" x="-492.570483" y="-25.482886" yaw="0.652420" z="10.286625" />
    <waypoint pitch="0.000000" roll="0.000000" time="11.100000" x="-492.452194" y="-25.443739" yaw="0.718476" z="10.288496" />
    <waypoint pitch="0.000000" roll="0.000000" time="11.300000" x="-492.213539" y="-25.465874" yaw="0.823659" z="10.290607" />
    <waypoint pitch="0.000000" roll="0.000000" time="11.500000" x="-491.976369" y="-25.470268" yaw="0.976744" z="10.293350" />
    <waypoint pitch="0.000000" roll="0.000000" time="11.700000" x="-491.737338" y="-25.474069" yaw="1.098600" z="10.295826" />
    <waypoint pitch="0.000000" roll="0.000000" time="12.100000" x="-491.261569" y="-25.477492" yaw="1.316456" z="10.297189" />
    <waypoint pitch="0.000000" roll="0.000000" time="12.500000" x="-491.261569" y="-25.477492" yaw="1.316456" z="10.298572" />
  </route>
</routes>