<?xml version='1.0' encoding='utf-8'?>
<routes>
  <route control_mode="replay" id="2023-04-04-15-47-17_19_1" model="walker.pedestrian.0002" role="walker" snap_to_road="false" town="ucla_v2">
    <waypoint pitch="0.000000" roll="0.000000" time="0.000000" x="-465.272952" y="101.417707" yaw="92.707724" z="7.952213" />
    <waypoint pitch="0.000000" roll="0.000000" time="0.400000" x="-465.225165" y="102.487781" yaw="92.562826" z="7.949786" />
    <waypoint pitch="0.000000" roll="0.000000" time="0.500000" x="-465.211942" y="102.575896" yaw="92.526596" z="7.947990" />
    <waypoint pitch="0.000000" roll="0.000000" time="0.600000" x="-465.199878" y="102.664043" yaw="92.490358" z="7.942141" />
    <waypoint pitch="0.000000" roll="0.000000" time="0.700000" x="-465.184956" y="102.752321" yaw="92.454133" z="7.940077" />
    <waypoint pitch="0.000000" roll="0.000000" time="0.900000" x="-465.162727" y="102.931959" yaw="92.381677" z="7.938007" />
    <waypoint pitch="0.000000" roll="0.000000" time="1.000000" x="-465.147771" y="103.020886" yaw="92.345449" z="7.935938" />
    <waypoint pitch="0.000000" roll="0.000000" time="1.100000" x="-465.130196" y="103.109875" yaw="92.309224" z="7.933852" />
    <waypoint pitch="0.000000" roll="0.000000" time="1.200000" x="-465.103855" y="103.196749" yaw="92.272994" z="7.932108" />
    <waypoint pitch="0.000000" roll="0.000000" time="1.300000" x="-465.111019" y="103.287920" yaw="92.236765" z="7.930353" />
    <waypoint pitch="0.000000" roll="0.000000" time="1.400000" x="-465.116134" y="103.378845" yaw="92.200526" z="7.928600" />
    <waypoint pitch="0.000000" roll="0.000000" time="1.500000" x="-465.108986" y="103.470108" yaw="92.170033" z="7.926832" />
    <waypoint pitch="0.000000" roll="0.000000" time="1.600000" x="-465.149386" y="103.556564" yaw="92.128069" z="7.922305" />
    <waypoint pitch="0.000000" roll="0.000000" time="1.700000" x="-465.174100" y="103.645327" yaw="92.097591" z="7.917983" />
    <waypoint pitch="0.000000" roll="0.000000" time="1.800000" x="-465.221308" y="104.438067" yaw="92.061358" z="7.913665" />
    <waypoint pitch="0.000000" roll="0.000000" time="1.900000" x="-465.239724" y="104.476207" yaw="92.025116" z="7.909588" />
    <waypoint pitch="0.000000" roll="0.000000" time="2.000000" x="-465.262709" y="104.565202" yaw="91.988886" z="7.905610" />
    <waypoint pitch="0.000000" roll="0.000000" time="2.100000" x="-465.276698" y="104.591305" yaw="91.958388" z="7.904500" />
    <waypoint pitch="0.000000" roll="0.000000" time="2.200000" x="-465.298886" y="104.654367" yaw="91.922145" z="7.903189" />
    <waypoint pitch="0.000000" roll="0.000000" time="2.300000" x="-465.321002" y="104.717252" yaw="91.885941" z="7.901927" />
    <waypoint pitch="0.000000" roll="0.000000" time="2.400000" x="-465.332759" y="104.806874" yaw="91.849693" z="7.900421" />
    <waypoint pitch="0.000000" roll="0.000000" time="2.500000" x="-465.297256" y="104.886107" yaw="91.819183" z="7.898857" />
    <waypoint pitch="0.000000" roll="0.000000" time="2.600000" x="-465.283058" y="104.975560" yaw="91.777224" z="7.897308" />
    <waypoint pitch="0.000000" roll="0.000000" time="2.700000" x="-465.315950" y="105.052807" yaw="91.746684" z="7.895670" />
    <waypoint pitch="0.000000" roll="0.000000" time="2.800000" x="-465.271448" y="105.114532" yaw="94.616794" z="7.894058" />
    <waypoint pitch="0.000000" roll="0.000000" time="2.900000" x="-465.348766" y="105.224308" yaw="91.674196" z="7.892533" />
    <waypoint pitch="0.000000" roll="0.000000" time="3.000000" x="-465.337918" y="105.295230" yaw="91.626519" z="7.891018" />
    <waypoint pitch="0.000000" roll="0.000000" time="3.100000" x="-465.337035" y="105.362636" yaw="91.596027" z="7.889407" />
    <waypoint pitch="0.000000" roll="0.000000" time="3.200000" x="-465.351599" y="105.438553" yaw="91.548422" z="7.885115" />
    <waypoint pitch="0.000000" roll="0.000000" time="3.300000" x="-465.320293" y="105.525323" yaw="91.517919" z="7.880749" />
    <waypoint pitch="0.000000" roll="0.000000" time="3.400000" x="-465.364673" y="106.330011" yaw="91.475979" z="7.876375" />
    <waypoint pitch="0.000000" roll="0.000000" time="3.500000" x="-465.361243" y="106.420856" yaw="91.445543" z="7.871929" />
    <waypoint pitch="0.000000" roll="0.000000" time="3.600000" x="-465.367491" y="106.490274" yaw="91.403604" z="7.867546" />
    <waypoint pitch="0.000000" roll="0.000000" time="3.700000" x="-465.363229" y="106.586136" yaw="91.367393" z="7.844922" />
    <waypoint pitch="0.000000" roll="0.000000" time="3.800000" x="-465.366205" y="106.655379" yaw="91.325429" z="7.822305" />
    <waypoint pitch="0.000000" roll="0.000000" time="8.000000" x="-465.426798" y="112.144926" yaw="91.177574" z="7.799615" />
    <waypoint pitch="0.000000" roll="0.000000" time="8.100000" x="-465.433515" y="112.232572" yaw="91.147941" z="7.776951" />
    <waypoint pitch="0.000000" roll="0.000000" time="8.200000" x="-465.439440" y="112.320042" yaw="91.148069" z="7.754211" />
    <waypoint pitch="0.000000" roll="0.000000" time="8.300000" x="-465.444621" y="112.407311" yaw="91.148138" z="7.752652" />
    <waypoint pitch="0.000000" roll="0.000000" time="8.400000" x="-465.443150" y="112.495660" yaw="91.124018" z="7.751248" />
    <waypoint pitch="0.000000" roll="0.000000" time="8.500000" x="-465.450027" y="112.541976" yaw="91.118370" z="7.749839" />
    <waypoint pitch="0.000000" roll="0.000000" time="8.600000" x="-465.446004" y="112.590646" yaw="91.153644" z="7.748416" />
    <waypoint pitch="0.000000" roll="0.000000" time="8.700000" x="-465.454612" y="112.679161" yaw="91.147897" z="7.746992" />
    <waypoint pitch="0.000000" roll="0.000000" time="8.800000" x="-465.450751" y="112.770116" yaw="91.153861" z="7.745393" />
    <waypoint pitch="0.000000" roll="0.000000" time="8.900000" x="-465.457661" y="112.858586" yaw="91.148086" z="7.743633" />
    <waypoint pitch="0.000000" roll="0.000000" time="9.000000" x="-465.452096" y="112.949721" yaw="91.153948" z="7.741859" />
    <waypoint pitch="0.000000" roll="0.000000" time="9.100000" x="-465.458338" y="113.038281" yaw="91.118527" z="7.740090" />
    <waypoint pitch="0.000000" roll="0.000000" time="9.200000" x="-465.451123" y="113.129771" yaw="91.154429" z="7.738305" />
    <waypoint pitch="0.000000" roll="0.000000" time="9.300000" x="-465.453690" y="113.218677" yaw="91.148447" z="7.733715" />
    <waypoint pitch="0.000000" roll="0.000000" time="9.400000" x="-465.445845" y="113.310650" yaw="91.183306" z="7.729236" />
    <waypoint pitch="0.000000" roll="0.000000" time="9.500000" x="-465.466335" y="114.108474" yaw="91.177575" z="7.724886" />
    <waypoint pitch="0.000000" roll="0.000000" time="9.600000" x="-465.466344" y="114.169337" yaw="91.183314" z="7.720499" />
    <waypoint pitch="0.000000" roll="0.000000" time="9.700000" x="-465.474272" y="114.227886" yaw="91.177585" z="7.716188" />
    <waypoint pitch="0.000000" roll="0.000000" time="9.800000" x="-465.476897" y="114.327160" yaw="91.183313" z="7.714724" />
    <waypoint pitch="0.000000" roll="0.000000" time="9.900000" x="-465.485514" y="114.398325" yaw="91.177573" z="7.713146" />
    <waypoint pitch="0.000000" roll="0.000000" time="10.000000" x="-465.523460" y="114.476087" yaw="91.183312" z="7.711492" />
    <waypoint pitch="0.000000" roll="0.000000" time="10.100000" x="-465.592484" y="114.563537" yaw="91.177590" z="7.709892" />
    <waypoint pitch="0.000000" roll="0.000000" time="10.200000" x="-465.609131" y="114.640652" yaw="91.183312" z="7.708235" />
    <waypoint pitch="0.000000" roll="0.000000" time="10.300000" x="-465.614105" y="114.723801" yaw="91.177588" z="7.706559" />
    <waypoint pitch="0.000000" roll="0.000000" time="10.400000" x="-465.607025" y="114.809493" yaw="91.183305" z="7.704712" />
    <waypoint pitch="0.000000" roll="0.000000" time="10.500000" x="-465.620421" y="114.892361" yaw="91.177587" z="7.697361" />
    <waypoint pitch="0.000000" roll="0.000000" time="10.600000" x="-465.510265" y="115.025901" yaw="91.177587" z="7.689996" />
    <waypoint pitch="0.000000" roll="0.000000" time="11.500000" x="-465.702934" y="116.450579" yaw="91.177588" z="7.682628" />
    <waypoint pitch="0.000000" roll="0.000000" time="11.600000" x="-465.710878" y="116.535597" yaw="91.183317" z="7.675420" />
    <waypoint pitch="0.000000" roll="0.000000" time="11.700000" x="-465.741430" y="116.618939" yaw="91.183316" z="7.668248" />
    <waypoint pitch="0.000000" roll="0.000000" time="11.800000" x="-465.769796" y="116.660875" yaw="91.183307" z="7.666643" />
    <waypoint pitch="0.000000" roll="0.000000" time="11.900000" x="-465.794587" y="116.779836" yaw="91.183312" z="7.665135" />
    <waypoint pitch="0.000000" roll="0.000000" time="12.000000" x="-465.823427" y="116.838592" yaw="91.177586" z="7.663705" />
    <waypoint pitch="0.000000" roll="0.000000" time="12.100000" x="-465.840943" y="116.899789" yaw="91.183312" z="7.662324" />
    <waypoint pitch="0.000000" roll="0.000000" time="12.200000" x="-465.868747" y="116.964498" yaw="91.177575" z="7.660884" />
    <waypoint pitch="0.000000" roll="0.000000" time="12.300000" x="-465.886000" y="116.994143" yaw="91.183297" z="7.656196" />
    <waypoint pitch="0.000000" roll="0.000000" time="12.400000" x="-465.846943" y="117.126080" yaw="91.183314" z="7.654687" />
    <waypoint pitch="0.000000" roll="0.000000" time="12.500000" x="-465.816096" y="117.961607" yaw="91.183303" z="7.652619" />
  </route>
</routes>