<?xml version='1.0' encoding='utf-8'?>
<routes>
  <route control_mode="replay" id="2023-04-04-15-39-17_11_1" model="walker.pedestrian.0008" role="walker" snap_to_road="false" town="ucla_v2">
    <waypoint pitch="0.000000" roll="0.000000" time="0.000000" x="-447.558802" y="-12.650688" yaw="-82.492788" z="10.523885" />
    <waypoint pitch="0.000000" roll="0.000000" time="0.100000" x="-447.541275" y="-12.727209" yaw="-82.418238" z="10.524128" />
    <waypoint pitch="0.000000" roll="0.000000" time="0.200000" x="-447.526171" y="-12.813966" yaw="-82.326513" z="10.524390" />
    <waypoint pitch="0.000000" roll="0.000000" time="0.300000" x="-447.526584" y="-12.886777" yaw="-82.246296" z="10.524922" />
    <waypoint pitch="0.000000" roll="0.000000" time="0.400000" x="-447.514659" y="-12.979395" yaw="-82.194670" z="10.525490" />
    <waypoint pitch="0.000000" roll="0.000000" time="0.500000" x="-447.507901" y="-13.074767" yaw="-82.125845" z="10.526118" />
    <waypoint pitch="0.000000" roll="0.000000" time="0.600000" x="-447.497023" y="-13.182950" yaw="-82.068508" z="10.526799" />
    <waypoint pitch="0.000000" roll="0.000000" time="0.700000" x="-447.467642" y="-13.314207" yaw="-82.045611" z="10.527545" />
    <waypoint pitch="0.000000" roll="0.000000" time="0.800000" x="-447.453603" y="-13.431935" yaw="-81.982569" z="10.528244" />
    <waypoint pitch="0.000000" roll="0.000000" time="0.900000" x="-447.418918" y="-13.578031" yaw="-81.976862" z="10.528906" />
    <waypoint pitch="0.000000" roll="0.000000" time="1.000000" x="-447.436484" y="-13.642994" yaw="-81.925225" z="10.529479" />
    <waypoint pitch="0.000000" roll="0.000000" time="1.100000" x="-447.432254" y="-13.724430" yaw="-81.936694" z="10.530277" />
    <waypoint pitch="0.000000" roll="0.000000" time="1.200000" x="-447.454222" y="-13.797819" yaw="-81.873657" z="10.530954" />
    <waypoint pitch="0.000000" roll="0.000000" time="1.300000" x="-447.396745" y="-14.095926" yaw="-81.896586" z="10.531646" />
    <waypoint pitch="0.000000" roll="0.000000" time="1.400000" x="-447.410495" y="-14.149467" yaw="-81.844989" z="10.532310" />
    <waypoint pitch="0.000000" roll="0.000000" time="1.500000" x="-447.398092" y="-14.221244" yaw="-81.862175" z="10.532994" />
    <waypoint pitch="0.000000" roll="0.000000" time="1.600000" x="-447.404249" y="-14.282294" yaw="-81.827812" z="10.534582" />
    <waypoint pitch="0.000000" roll="0.000000" time="1.700000" x="-447.393836" y="-14.364332" yaw="-81.839285" z="10.536168" />
    <waypoint pitch="0.000000" roll="0.000000" time="2.300000" x="-447.204081" y="-15.364359" yaw="-81.822121" z="10.537836" />
    <waypoint pitch="0.000000" roll="0.000000" time="2.400000" x="-447.199044" y="-15.410511" yaw="-81.822125" z="10.539433" />
    <waypoint pitch="0.000000" roll="0.000000" time="2.500000" x="-447.198016" y="-15.549268" yaw="-81.822128" z="10.541086" />
    <waypoint pitch="0.000000" roll="0.000000" time="2.600000" x="-447.186315" y="-15.572845" yaw="-81.816388" z="10.541563" />
    <waypoint pitch="0.000000" roll="0.000000" time="2.700000" x="-447.136038" y="-15.668308" yaw="-81.822127" z="10.542177" />
    <waypoint pitch="0.000000" roll="0.000000" time="2.800000" x="-447.150457" y="-15.750961" yaw="-81.822122" z="10.542757" />
    <waypoint pitch="0.000000" roll="0.000000" time="2.900000" x="-447.122788" y="-15.910061" yaw="-81.822124" z="10.543474" />
    <waypoint pitch="0.000000" roll="0.000000" time="3.000000" x="-447.120063" y="-16.023428" yaw="-81.822127" z="10.544201" />
    <waypoint pitch="0.000000" roll="0.000000" time="3.100000" x="-447.101578" y="-16.132099" yaw="-81.827868" z="10.544935" />
    <waypoint pitch="0.000000" roll="0.000000" time="3.200000" x="-447.125309" y="-16.269559" yaw="-81.822124" z="10.545587" />
    <waypoint pitch="0.000000" roll="0.000000" time="3.300000" x="-447.114369" y="-16.354483" yaw="-81.822126" z="10.546178" />
    <waypoint pitch="0.000000" roll="0.000000" time="3.400000" x="-447.135150" y="-16.449674" yaw="-81.822134" z="10.546761" />
    <waypoint pitch="0.000000" roll="0.000000" time="3.500000" x="-447.148753" y="-16.512670" yaw="-81.822123" z="10.547296" />
    <waypoint pitch="0.000000" roll="0.000000" time="3.600000" x="-447.151196" y="-16.618690" yaw="-81.822120" z="10.548095" />
    <waypoint pitch="0.000000" roll="0.000000" time="3.700000" x="-447.132203" y="-16.712523" yaw="-81.822122" z="10.548417" />
    <waypoint pitch="0.000000" roll="0.000000" time="3.800000" x="-447.088318" y="-17.008507" yaw="-81.822126" z="10.548828" />
  </route>
</routes>