<?xml version='1.0' encoding='utf-8'?>
<routes>
  <route control_mode="replay" id="2023-04-04-14-30-53_47_0" model="vehicle.carlamotors.carlacola" role="static" snap_to_road="false" town="ucla_v2">
    <waypoint pitch="-0.601508" roll="-1.658348" time="0.000000" x="-499.564114" y="-53.545536" yaw="49.169871" z="10.736792" />
    <waypoint pitch="-0.598714" roll="-1.658821" time="0.100000" x="-499.534201" y="-53.565916" yaw="49.637054" z="10.736899" />
    <waypoint pitch="-0.597803" roll="-1.657611" time="0.200000" x="-499.599809" y="-53.535405" yaw="49.706922" z="10.737012" />
    <waypoint pitch="-0.600782" roll="-1.656640" time="0.300000" x="-499.474923" y="-53.511825" yaw="49.140885" z="10.737788" />
    <waypoint pitch="-0.598545" roll="-1.655840" time="0.400000" x="-499.528365" y="-53.567766" yaw="49.193494" z="10.737882" />
    <waypoint pitch="-0.596881" roll="-1.660245" time="0.500000" x="-499.459414" y="-53.631122" yaw="49.667243" z="10.737937" />
    <waypoint pitch="-0.595602" roll="-1.662615" time="0.600000" x="-499.519347" y="-53.561310" yaw="49.154943" z="10.737683" />
    <waypoint pitch="-0.596460" roll="-1.667255" time="0.700000" x="-499.508602" y="-53.481850" yaw="49.128851" z="10.737475" />
    <waypoint pitch="-0.595379" roll="-1.665115" time="0.800000" x="-499.557608" y="-53.501462" yaw="49.154425" z="10.736508" />
    <waypoint pitch="-0.596127" roll="-1.662456" time="0.900000" x="-499.593311" y="-53.561002" yaw="49.622392" z="10.736049" />
    <waypoint pitch="-0.598060" roll="-1.659832" time="1.000000" x="-499.563190" y="-53.515498" yaw="49.637003" z="10.736337" />
    <waypoint pitch="-0.599083" roll="-1.656673" time="1.100000" x="-499.564775" y="-53.495752" yaw="49.618612" z="10.736487" />
    <waypoint pitch="-0.600556" roll="-1.653549" time="1.200000" x="-499.547377" y="-53.576405" yaw="49.637015" z="10.736517" />
    <waypoint pitch="-0.601317" roll="-1.658639" time="1.300000" x="-499.574116" y="-53.539310" yaw="49.128786" z="10.736630" />
    <waypoint pitch="-0.601317" roll="-1.658639" time="1.400000" x="-499.503051" y="-53.504330" yaw="49.616833" z="10.736630" />
    <waypoint pitch="-0.599962" roll="-1.653988" time="1.500000" x="-499.511920" y="-53.488713" yaw="49.595215" z="10.736532" />
    <waypoint pitch="-0.607715" roll="-1.650556" time="1.600000" x="-499.569593" y="-53.493110" yaw="49.631651" z="10.736120" />
    <waypoint pitch="-0.607353" roll="-1.652384" time="1.700000" x="-499.551044" y="-53.540332" yaw="49.614010" z="10.736081" />
    <waypoint pitch="-0.608302" roll="-1.650314" time="1.800000" x="-499.620534" y="-53.505366" yaw="50.635464" z="10.736343" />
    <waypoint pitch="-0.609792" roll="-1.653773" time="1.900000" x="-499.542271" y="-53.493326" yaw="49.616929" z="10.736709" />
    <waypoint pitch="-0.614045" roll="-1.658329" time="2.000000" x="-499.502860" y="-53.552954" yaw="49.679422" z="10.736680" />
    <waypoint pitch="-0.609290" roll="-1.658675" time="2.100000" x="-499.522909" y="-53.547200" yaw="49.620862" z="10.737381" />
    <waypoint pitch="-0.610018" roll="-1.657044" time="2.200000" x="-499.532734" y="-53.524050" yaw="50.141091" z="10.737634" />
    <waypoint pitch="-0.608949" roll="-1.656154" time="2.300000" x="-499.571354" y="-53.612117" yaw="49.619252" z="10.737015" />
    <waypoint pitch="-0.607460" roll="-1.652695" time="2.400000" x="-499.511603" y="-53.555969" yaw="49.633940" z="10.736649" />
    <waypoint pitch="-0.600636" roll="-1.650825" time="2.500000" x="-499.614158" y="-53.492495" yaw="49.619441" z="10.736289" />
    <waypoint pitch="-0.597931" roll="-1.654674" time="2.600000" x="-499.568032" y="-53.499355" yaw="49.644682" z="10.735773" />
    <waypoint pitch="-0.601362" roll="-1.652813" time="2.700000" x="-499.614163" y="-53.514850" yaw="49.129428" z="10.736041" />
    <waypoint pitch="-0.596788" roll="-1.657796" time="2.800000" x="-499.492969" y="-53.460431" yaw="49.150354" z="10.736485" />
    <waypoint pitch="-0.596788" roll="-1.657796" time="2.900000" x="-499.461982" y="-53.570759" yaw="50.153695" z="10.736485" />
    <waypoint pitch="-0.606001" roll="-1.661390" time="3.000000" x="-499.479478" y="-53.514653" yaw="48.671655" z="10.736745" />
    <waypoint pitch="-0.613058" roll="-1.660374" time="3.100000" x="-499.571733" y="-53.515053" yaw="49.782597" z="10.737008" />
    <waypoint pitch="-0.621173" roll="-1.656197" time="3.200000" x="-499.564387" y="-53.527703" yaw="50.668018" z="10.736570" />
    <waypoint pitch="-0.640103" roll="-1.644744" time="3.300000" x="-499.561507" y="-53.521632" yaw="50.363630" z="10.736603" />
    <waypoint pitch="-0.654844" roll="-1.642284" time="3.400000" x="-499.625436" y="-53.580328" yaw="51.773367" z="10.737078" />
    <waypoint pitch="-0.659916" roll="-1.635902" time="3.500000" x="-499.543693" y="-53.527338" yaw="51.870901" z="10.736960" />
    <waypoint pitch="-0.665765" roll="-1.630939" time="3.600000" x="-499.554280" y="-53.590413" yaw="51.938058" z="10.736810" />
    <waypoint pitch="-0.666787" roll="-1.632412" time="3.700000" x="-499.576256" y="-53.522025" yaw="51.539583" z="10.737062" />
    <waypoint pitch="-0.651512" roll="-1.645254" time="3.800000" x="-499.554440" y="-53.524819" yaw="51.424983" z="10.736996" />
    <waypoint pitch="-0.637116" roll="-1.657419" time="3.900000" x="-499.560624" y="-53.579637" yaw="51.813544" z="10.736754" />
    <waypoint pitch="-0.619307" roll="-1.658227" time="4.000000" x="-499.580901" y="-53.575560" yaw="49.120825" z="10.736341" />
    <waypoint pitch="-0.603661" roll="-1.664381" time="4.100000" x="-499.511031" y="-53.525526" yaw="49.103798" z="10.736572" />
    <waypoint pitch="-0.584271" roll="-1.672163" time="4.200000" x="-499.637581" y="-53.471743" yaw="48.656873" z="10.736065" />
    <waypoint pitch="-0.581818" roll="-1.667096" time="4.300000" x="-499.532605" y="-53.530964" yaw="48.606813" z="10.736097" />
    <waypoint pitch="-0.577751" roll="-1.662818" time="4.400000" x="-499.589439" y="-53.505394" yaw="48.659074" z="10.735927" />
    <waypoint pitch="-0.581291" roll="-1.667169" time="4.500000" x="-499.566354" y="-53.564848" yaw="48.652751" z="10.736521" />
    <waypoint pitch="-0.582248" roll="-1.669206" time="4.600000" x="-499.525524" y="-53.517173" yaw="48.646428" z="10.736290" />
    <waypoint pitch="-0.586453" roll="-1.669136" time="4.700000" x="-499.556432" y="-53.558742" yaw="49.104559" z="10.736481" />
    <waypoint pitch="-0.585636" roll="-1.670754" time="4.800000" x="-499.523025" y="-53.509555" yaw="48.660429" z="10.736515" />
    <waypoint pitch="-0.586105" roll="-1.670937" time="4.900000" x="-499.589084" y="-53.546982" yaw="49.102217" z="10.736478" />
    <waypoint pitch="-0.583990" roll="-1.673803" time="5.000000" x="-499.551291" y="-53.532984" yaw="48.653869" z="10.736390" />
    <waypoint pitch="-0.584500" roll="-1.674090" time="5.100000" x="-499.564518" y="-53.497002" yaw="49.133034" z="10.736572" />
    <waypoint pitch="-0.581604" roll="-1.671569" time="5.200000" x="-499.595054" y="-53.547216" yaw="48.656161" z="10.736436" />
    <waypoint pitch="-0.578518" roll="-1.663035" time="5.300000" x="-499.554905" y="-53.545967" yaw="49.103609" z="10.736760" />
    <waypoint pitch="-0.578767" roll="-1.658838" time="5.400000" x="-499.580534" y="-53.493043" yaw="48.660550" z="10.737411" />
    <waypoint pitch="-0.580935" roll="-1.655865" time="5.500000" x="-499.527191" y="-53.579336" yaw="48.604827" z="10.737502" />
    <waypoint pitch="-0.580900" roll="-1.653531" time="5.600000" x="-499.490845" y="-53.576930" yaw="49.157379" z="10.737109" />
    <waypoint pitch="-0.582943" roll="-1.654548" time="5.700000" x="-499.557559" y="-53.556545" yaw="49.099503" z="10.737445" />
    <waypoint pitch="-0.586845" roll="-1.661465" time="5.800000" x="-499.612526" y="-53.501689" yaw="49.115897" z="10.737087" />
    <waypoint pitch="-0.587700" roll="-1.665488" time="5.900000" x="-499.518167" y="-53.528766" yaw="49.135344" z="10.736747" />
    <waypoint pitch="-0.583471" roll="-1.665533" time="6.000000" x="-499.575336" y="-53.541642" yaw="48.624520" z="10.736638" />
    <waypoint pitch="-0.583173" roll="-1.667207" time="6.100000" x="-499.504027" y="-53.542667" yaw="49.102853" z="10.737018" />
    <waypoint pitch="-0.580621" roll="-1.665206" time="6.200000" x="-499.556801" y="-53.525621" yaw="48.667320" z="10.736987" />
    <waypoint pitch="-0.579804" roll="-1.666823" time="6.300000" x="-499.557075" y="-53.530590" yaw="48.602799" z="10.737022" />
    <waypoint pitch="-0.576334" roll="-1.666961" time="6.400000" x="-499.547687" y="-53.542694" yaw="48.625334" z="10.736471" />
    <waypoint pitch="-0.577626" roll="-1.669495" time="6.500000" x="-499.560654" y="-53.535286" yaw="48.602873" z="10.736308" />
    <waypoint pitch="-0.579150" roll="-1.665786" time="6.600000" x="-499.560145" y="-53.462592" yaw="48.656157" z="10.736685" />
    <waypoint pitch="-0.580137" roll="-1.667740" time="6.700000" x="-499.595539" y="-53.491861" yaw="48.605029" z="10.736616" />
    <waypoint pitch="-0.580955" roll="-1.666123" time="6.800000" x="-499.542538" y="-53.606400" yaw="49.144630" z="10.736582" />
    <waypoint pitch="-0.582551" roll="-1.664634" time="6.900000" x="-499.558785" y="-53.542426" yaw="48.618246" z="10.736789" />
    <waypoint pitch="-0.580587" roll="-1.664076" time="7.000000" x="-499.564791" y="-53.536873" yaw="48.634169" z="10.736707" />
    <waypoint pitch="-0.576702" roll="-1.663114" time="7.100000" x="-499.582308" y="-53.513791" yaw="48.593749" z="10.736428" />
    <waypoint pitch="-0.579067" roll="-1.664772" time="7.200000" x="-499.580170" y="-53.475041" yaw="48.619175" z="10.736325" />
    <waypoint pitch="-0.576929" roll="-1.663776" time="7.300000" x="-499.556652" y="-53.571911" yaw="48.630811" z="10.736414" />
    <waypoint pitch="-0.579056" roll="-1.662802" time="7.400000" x="-499.588768" y="-53.560974" yaw="49.120407" z="10.736610" />
    <waypoint pitch="-0.582420" roll="-1.662527" time="7.500000" x="-499.548764" y="-53.548272" yaw="48.604019" z="10.736808" />
    <waypoint pitch="-0.587665" roll="-1.669859" time="7.600000" x="-499.565741" y="-53.534350" yaw="49.118808" z="10.736753" />
    <waypoint pitch="-0.584347" roll="-1.663080" time="7.700000" x="-499.547911" y="-53.519645" yaw="48.602953" z="10.736748" />
    <waypoint pitch="-0.588320" roll="-1.667894" time="7.800000" x="-499.537334" y="-53.534303" yaw="49.619163" z="10.736643" />
    <waypoint pitch="-0.587489" roll="-1.668219" time="7.900000" x="-499.574524" y="-53.530002" yaw="48.601676" z="10.736650" />
    <waypoint pitch="-0.588209" roll="-1.668090" time="8.000000" x="-499.505465" y="-53.510413" yaw="49.122634" z="10.736841" />
    <waypoint pitch="-0.583356" roll="-1.664054" time="8.100000" x="-499.577048" y="-53.532739" yaw="48.599704" z="10.736854" />
    <waypoint pitch="-0.583830" roll="-1.668206" time="8.200000" x="-499.549510" y="-53.555332" yaw="49.120391" z="10.736725" />
    <waypoint pitch="-0.581380" roll="-1.663383" time="8.300000" x="-499.611605" y="-53.588997" yaw="48.602918" z="10.736837" />
    <waypoint pitch="-0.579576" roll="-1.663046" time="8.400000" x="-499.578956" y="-53.492021" yaw="48.620723" z="10.736940" />
    <waypoint pitch="-0.580703" roll="-1.659915" time="8.500000" x="-499.579485" y="-53.588743" yaw="49.102898" z="10.736610" />
    <waypoint pitch="-0.583489" roll="-1.659673" time="8.600000" x="-499.548505" y="-53.532151" yaw="48.621955" z="10.736519" />
    <waypoint pitch="-0.582307" roll="-1.662032" time="8.700000" x="-499.634343" y="-53.541038" yaw="49.100633" z="10.736990" />
    <waypoint pitch="-0.581467" roll="-1.667422" time="8.800000" x="-499.584285" y="-53.568168" yaw="48.608963" z="10.736699" />
    <waypoint pitch="-0.583271" roll="-1.667758" time="8.900000" x="-499.486677" y="-53.562818" yaw="48.615780" z="10.736595" />
    <waypoint pitch="-0.580792" roll="-1.672245" time="9.000000" x="-499.609503" y="-53.562470" yaw="48.623636" z="10.736801" />
    <waypoint pitch="-0.581576" roll="-1.671827" time="9.100000" x="-499.579010" y="-53.555053" yaw="48.598757" z="10.736685" />
    <waypoint pitch="-0.580975" roll="-1.667907" time="9.200000" x="-499.588036" y="-53.550266" yaw="48.617377" z="10.736288" />
    <waypoint pitch="-0.584808" roll="-1.666473" time="9.300000" x="-499.555301" y="-53.518692" yaw="49.138815" z="10.736407" />
    <waypoint pitch="-0.586929" roll="-1.665791" time="9.400000" x="-499.579394" y="-53.522452" yaw="48.619981" z="10.735858" />
    <waypoint pitch="-0.586187" roll="-1.664783" time="9.500000" x="-499.569831" y="-53.558564" yaw="49.599818" z="10.735367" />
    <waypoint pitch="-0.587150" roll="-1.666532" time="9.600000" x="-499.604710" y="-53.468146" yaw="49.654322" z="10.735097" />
    <waypoint pitch="-0.587505" roll="-1.669249" time="9.700000" x="-499.654687" y="-53.492527" yaw="48.599359" z="10.734759" />
    <waypoint pitch="-0.585834" roll="-1.664207" time="9.800000" x="-499.632537" y="-53.517521" yaw="49.116450" z="10.735246" />
    <waypoint pitch="-0.582860" roll="-1.664008" time="9.900000" x="-499.593164" y="-53.465989" yaw="48.600395" z="10.736281" />
    <waypoint pitch="-0.586383" roll="-1.662655" time="10.000000" x="-499.535777" y="-53.622993" yaw="49.119457" z="10.737153" />
    <waypoint pitch="-0.586775" roll="-1.663430" time="10.100000" x="-499.505576" y="-53.599069" yaw="49.132515" z="10.737297" />
    <waypoint pitch="-0.588786" roll="-1.664171" time="10.200000" x="-499.502983" y="-53.555429" yaw="49.150855" z="10.737618" />
    <waypoint pitch="-0.586063" roll="-1.668029" time="10.300000" x="-499.606040" y="-53.532948" yaw="49.097283" z="10.737330" />
    <waypoint pitch="-0.588517" roll="-1.672080" time="10.400000" x="-499.529581" y="-53.502870" yaw="49.116252" z="10.736777" />
    <waypoint pitch="-0.585136" roll="-1.674382" time="10.500000" x="-499.597030" y="-53.600628" yaw="49.144495" z="10.736195" />
    <waypoint pitch="-0.583349" roll="-1.671490" time="10.600000" x="-499.587311" y="-53.555379" yaw="49.098405" z="10.736163" />
    <waypoint pitch="-0.591203" roll="-1.668436" time="10.700000" x="-499.606908" y="-53.522747" yaw="48.633363" z="10.736377" />
    <waypoint pitch="-0.594579" roll="-1.667883" time="10.800000" x="-499.541541" y="-53.461036" yaw="49.118639" z="10.736021" />
    <waypoint pitch="-0.593791" roll="-1.661442" time="10.900000" x="-499.507409" y="-53.514414" yaw="50.129368" z="10.735675" />
    <waypoint pitch="-0.598955" roll="-1.654433" time="11.000000" x="-499.527088" y="-53.475052" yaw="49.149050" z="10.735755" />
    <waypoint pitch="-0.605474" roll="-1.655311" time="11.100000" x="-499.627361" y="-53.478881" yaw="49.128832" z="10.735733" />
    <waypoint pitch="-0.598228" roll="-1.654132" time="11.200000" x="-499.583842" y="-53.513937" yaw="49.612086" z="10.736033" />
    <waypoint pitch="-0.597252" roll="-1.653290" time="11.300000" x="-499.614625" y="-53.513811" yaw="50.128807" z="10.736165" />
    <waypoint pitch="-0.599602" roll="-1.657566" time="11.400000" x="-499.474462" y="-53.561060" yaw="49.145847" z="10.736480" />
    <waypoint pitch="-0.596348" roll="-1.663175" time="11.500000" x="-499.555084" y="-53.515163" yaw="49.088027" z="10.736506" />
    <waypoint pitch="-0.589857" roll="-1.662353" time="11.600000" x="-499.515324" y="-53.488514" yaw="50.108395" z="10.736611" />
    <waypoint pitch="-0.592692" roll="-1.660604" time="11.700000" x="-499.569208" y="-53.499476" yaw="49.129757" z="10.736046" />
    <waypoint pitch="-0.599366" roll="-1.661250" time="11.800000" x="-499.524355" y="-53.490484" yaw="49.147614" z="10.736266" />
    <waypoint pitch="-0.601994" roll="-1.657367" time="11.900000" x="-499.572237" y="-53.512168" yaw="50.092010" z="10.736527" />
    <waypoint pitch="-0.612586" roll="-1.648891" time="12.000000" x="-499.578155" y="-53.573279" yaw="50.108940" z="10.736686" />
    <waypoint pitch="-0.618618" roll="-1.646721" time="12.100000" x="-499.615041" y="-53.608113" yaw="50.089520" z="10.736895" />
    <waypoint pitch="-0.624756" roll="-1.647614" time="12.200000" x="-499.583914" y="-53.552072" yaw="50.609093" z="10.737255" />
  </route>
</routes>